{"title":"","slug":"qqqq","date":"2019-01-02T13:17:24.287Z","updated":"2019-01-02T13:17:24.287Z","comments":true,"path":"api/articles/qqqq.json","photos":[],"link":"","excerpt":null,"covers":["https://luoyuanoo-1258347275.cos.ap-chongqing.myqcloud.com/1.jpg","https://luoyuanoo-1258347275.cos.ap-chongqing.myqcloud.com/1.jpg"],"content":"<p><img src=\"https://luoyuanoo-1258347275.cos.ap-chongqing.myqcloud.com/1.jpg\" alt=\"罗元简历\"></p>\n<p><img src=\"https://luoyuanoo-1258347275.cos.ap-chongqing.myqcloud.com/1.jpg\" alt=\"hhh\"></p>\n","categories":[],"tags":[]}